sparta_rabbit-0.0.8-py3.11-nspkg.pth
sparta/rabbit/__init__.py
sparta/rabbit/client.py
sparta/rabbit/connection.py
sparta_rabbit-0.0.8.dist-info/LICENSE
sparta_rabbit-0.0.8.dist-info/METADATA
sparta_rabbit-0.0.8.dist-info/WHEEL
sparta_rabbit-0.0.8.dist-info/namespace_packages.txt
sparta_rabbit-0.0.8.dist-info/top_level.txt
sparta_rabbit-0.0.8.dist-info/RECORD
