Metadata-Version: 2.1
Name: sparta-rabbit
Version: 0.0.8
Summary: Sparta rabbit library
Home-page: https://github.com/Spartan-Approach/sparta-rabbit
Author: Spartan Approach
Author-email: sparta@spartanapproach.com
Classifier: Development Status :: 4 - Beta
Classifier: Programming Language :: Python :: 3
Classifier: License :: OSI Approved :: MIT License
Classifier: Operating System :: OS Independent
Requires-Python: >=3.9
License-File: LICENSE
Requires-Dist: pika
Requires-Dist: pika-stubs
Requires-Dist: aio-pika
Provides-Extra: test
Requires-Dist: pytest ; extra == 'test'
Requires-Dist: pytest-asyncio ; extra == 'test'
Requires-Dist: python-dotenv ; extra == 'test'
